dreamai_gen/__init__.py
dreamai_gen/asking.py
dreamai_gen/chroma.py
dreamai_gen/g_apis/__init__.py
dreamai_gen/g_apis/auth.py
dreamai_gen/g_apis/quiz.py
dreamai_gen/g_apis/slides.py
dreamai_gen/llms.py
dreamai_gen/message.py
dreamai_gen/pdf.py
dreamai_gen/prompting/__init__.py
dreamai_gen/prompting/edu_prompt_fns.py
dreamai_gen/prompting/edu_prompt_strs.py
dreamai_gen/prompting/prompt_fns.py
dreamai_gen/prompting/prompt_strs.py
dreamai_gen/recipes.py
dreamai_gen/tools.py
dreamai_gen/utils.py
dreamai_gen-0.1.15.dist-info/METADATA
dreamai_gen-0.1.15.dist-info/WHEEL
dreamai_gen-0.1.15.dist-info/RECORD
