Metadata-Version: 2.1
Name: dreamai-gen
Version: 0.1.15
Summary: 
Author: Hamza Farhan
Author-email: thehamza96@gmail.com
Requires-Python: >=3.11,<3.12
Classifier: Programming Language :: Python :: 3
Classifier: Programming Language :: Python :: 3.11
Requires-Dist: anthropic (>=0.19.1,<0.20.0)
Requires-Dist: chromadb (>=0.4.24,<0.5.0)
Requires-Dist: demoji (>=1.1.0,<2.0.0)
Requires-Dist: dspy-ai (>=2.4.0,<3.0.0)
Requires-Dist: duckduckgo-search (>=5.0,<6.0)
Requires-Dist: fastcore (>=1.5.29,<2.0.0)
Requires-Dist: google-api-python-client (>=2.121.0,<3.0.0)
Requires-Dist: google-auth-oauthlib (>=1.2.0,<2.0.0)
Requires-Dist: google-cloud-api-keys (>=0.5.9,<0.6.0)
Requires-Dist: google-generativeai (>=0.4.0,<0.5.0)
Requires-Dist: instructor (>=0.6.8,<0.7.0)
Requires-Dist: ipython (>=8.22.2,<9.0.0)
Requires-Dist: ipywidgets (>=8.1.2,<9.0.0)
Requires-Dist: lancedb (>=0.6.2,<0.7.0)
Requires-Dist: langchain (>=0.1.11,<0.2.0)
Requires-Dist: litellm[proxy] (>=1.30.3,<2.0.0)
Requires-Dist: marvin (>=2.1.6,<3.0.0)
Requires-Dist: modal (>=0.61.95,<0.62.0)
Requires-Dist: notebook (>=7.1.1,<8.0.0)
Requires-Dist: open-clip-torch (>=2.24.0,<3.0.0)
Requires-Dist: openai (>=1.13.3,<2.0.0)
Requires-Dist: opencv-python-headless (>=4.9.0.80,<5.0.0.0)
Requires-Dist: openpyxl (>=3.1.2,<4.0.0)
Requires-Dist: polars (>=0.20.17,<0.21.0)
Requires-Dist: pyngrok (>=7.1.5,<8.0.0)
Requires-Dist: pytest (>=8.0.2,<9.0.0)
Requires-Dist: python-dotenv (>=1.0.1,<2.0.0)
Requires-Dist: ruff (>=0.3.1,<0.4.0)
Requires-Dist: sentence-transformers (>=2.5.1,<3.0.0)
Requires-Dist: streamlit (>=1.32.0,<2.0.0)
Requires-Dist: tantivy (>=0.21.0,<0.22.0)
Requires-Dist: tenacity (>=8.2.3,<9.0.0)
Requires-Dist: termcolor (>=2.4.0,<3.0.0)
Requires-Dist: tiktoken (>=0.6.0,<0.7.0)
Requires-Dist: unstructured[pdf] (>=0.12.5,<0.13.0)
